yatr/__init__.py
yatr/base.py
yatr/context.py
yatr/env.py
yatr/env_decorators.py
yatr/main.py
yatr/parse.py
yatr/task.py
yatr/scripts/completion/yatr
yatr/tests/__init__.py
yatr/tests/mod1.py
yatr/tests/mod2.py
yatr/tests/test_base.py
yatr/tests/test_context.py
yatr/tests/test_env.py
yatr/tests/test_env_decorators.py
yatr/tests/test_parse.py
yatr/tests/test_task.py
yatr/tests/yatrfile1.yml
yatr-0.0.10.dist-info/DESCRIPTION.rst
yatr-0.0.10.dist-info/METADATA
yatr-0.0.10.dist-info/RECORD
yatr-0.0.10.dist-info/WHEEL
yatr-0.0.10.dist-info/entry_points.txt
yatr-0.0.10.dist-info/metadata.json
yatr-0.0.10.dist-info/top_level.txt
